hsim/__init__.py
hsim-0.0.1.dist-info/METADATA
hsim-0.0.1.dist-info/WHEEL
hsim-0.0.1.dist-info/RECORD
